MegaLib/Utils.py
MegaLib/__init__.py
MegaLib/networking.py
MegaLib2/Utils.py
MegaLib2/__init__.py
MegaLib2/networking.py
MegaLib2-0.0.2.dist-info/METADATA
MegaLib2-0.0.2.dist-info/WHEEL
MegaLib2-0.0.2.dist-info/top_level.txt
MegaLib2-0.0.2.dist-info/RECORD
